sentry_dingding/__init__.py
sentry_dingding/forms.py
sentry_dingding/plugin.py
sentry_dingding_feelys-0.2.0.dist-info/LICENSE
sentry_dingding_feelys-0.2.0.dist-info/METADATA
sentry_dingding_feelys-0.2.0.dist-info/WHEEL
sentry_dingding_feelys-0.2.0.dist-info/entry_points.txt
sentry_dingding_feelys-0.2.0.dist-info/top_level.txt
sentry_dingding_feelys-0.2.0.dist-info/RECORD
