Metadata-Version: 2.1
Name: sentry-dingding-feelys
Version: 0.2.0
Summary: A Sentry extension which send errors stats to DingDing
Home-page: https://github.com/lcfevr/sentry-dingding-feelys
Author: lcfevr
Author-email: lcfevr@163.com
License: MIT
Keywords: sentry dingding feelys
Platform: UNKNOWN
Classifier: Programming Language :: Python :: 2.7
Classifier: License :: OSI Approved :: MIT License
Requires-Dist: sentry (>=9.0.0)
Requires-Dist: requests
